faithscore/COCO_val2014_000000164255.jpg
faithscore/__init__.py
faithscore/framework.py
faithscore/llama_pre.py
faithscore/llava15.py
faithscore/test_fact.py
faithscore/utils.py
faithscore/prompts/prompt_de_atomic.txt
faithscore/prompts/prompt_label_des_ana.txt
faithscore/prompts/prompt_llama.txt
faithscore-0.0.9.dist-info/METADATA
faithscore-0.0.9.dist-info/WHEEL
faithscore-0.0.9.dist-info/licenses/LICENSE
faithscore-0.0.9.dist-info/RECORD
