Metadata-Version: 2.1
Name: faithscore
Version: 0.0.9
Summary: Faithscore is a noverl metric for evaluating hallucinations in large vision-language models!
Project-URL: Homepage, https://github.com/bcdnlp/FAITHSCORE
Author-email: Liqiang Jing <jingliqiang6@gmail.com>
License: MIT License
License-File: LICENSE
Classifier: License :: OSI Approved :: MIT License
Classifier: Operating System :: OS Independent
Classifier: Programming Language :: Python :: 3
Requires-Python: >=3.7
Requires-Dist: nltk
Requires-Dist: openai==0.27
Requires-Dist: pillow
Requires-Dist: tqdm
